dbtq/__init__.py
dbtq/main.py
dbtq-0.0.1.dist-info/METADATA
dbtq-0.0.1.dist-info/WHEEL
dbtq-0.0.1.dist-info/entry_points.txt
dbtq-0.0.1.dist-info/top_level.txt
dbtq-0.0.1.dist-info/RECORD
