Metadata-Version: 2.1
Name: dbtq
Version: 0.0.1
Summary: Query compiled dbt models locally
Author: Ethan Brown
Author-email: ethan.w.brown@gmail.com
Requires-Python: >=3.6
Requires-Dist: pandas
Requires-Dist: pyyaml
Requires-Dist: psycopg2[binary]
Requires-Dist: rich
Requires-Dist: rich-tools
Requires-Dist: sqlalchemy
Requires-Dist: typer[all]
